Slugi_class/__init__.py
Slugi_class/slugify.py
Slugify_classmodule-1.0.1.dist-info/METADATA
Slugify_classmodule-1.0.1.dist-info/WHEEL
Slugify_classmodule-1.0.1.dist-info/top_level.txt
Slugify_classmodule-1.0.1.dist-info/RECORD
